enot/__init__.py
enot/__main__.py
enot/global_properties.py
enot/action/__init__.py
enot/action/action.py
enot/action/action_factory.py
enot/action/release.py
enot/action/shell.py
enot/compiler/__init__.py
enot/compiler/abstract.py
enot/compiler/bootstrap.py
enot/compiler/c_compiler.py
enot/compiler/compiler_factory.py
enot/compiler/compiler_type.py
enot/compiler/enot.py
enot/compiler/erlang_mk.py
enot/compiler/makefile.py
enot/compiler/rebar.py
enot/compiler/rebar3.py
enot/compiler/relx.py
enot/pac_cache/__init__.py
enot/pac_cache/cache.py
enot/pac_cache/cache_factory.py
enot/pac_cache/cache_man.py
enot/pac_cache/enot_cache.py
enot/pac_cache/local_cache.py
enot/pac_cache/remote_cache.py
enot/pac_cache/remote_cache_exception.py
enot/packages/__init__.py
enot/packages/application_config.py
enot/packages/dep.py
enot/packages/package.py
enot/packages/package_builder.py
enot/packages/package_controller.py
enot/packages/config/__init__.py
enot/packages/config/config.py
enot/packages/config/config_factory.py
enot/packages/config/dep_config.py
enot/packages/config/enot.py
enot/packages/config/erlang_mk.py
enot/packages/config/rebar.py
enot/resources/CMakefile
enot/resources/EmptyMakefile
enot/resources/__init__.py
enot/resources/global_config.json
enot/resources/relx.config
enot/resources/sys.config
enot/resources/template.app.src
enot/resources/template_app.erl
enot/resources/template_sup.erl
enot/resources/templateenot_config.json
enot/resources/vm.args
enot/tool/__init__.py
enot/tool/erlang_mk.py
enot/tool/rebar.py
enot/tool/rebar3.py
enot/tool/relxtool.py
enot/tool/tool.py
enot/utils/__init__.py
enot/utils/erl_file_utils.py
enot/utils/file_utils.py
enot/utils/http_utils.py
enot/utils/logger.py
test/__init__.py
test/abs_test_class.py
test/test_applications.py
test/test_build.py
test/test_controller_api.py
test/test_create.py
test/test_packages.py
test/test_rebar_config.py
test/test_tests.py
test/test_tools.py
test/cache/__init__.py
test/cache/test_enot_cache.py
enot-2.1.8.dist-info/LICENSE
enot-2.1.8.dist-info/METADATA
enot-2.1.8.dist-info/WHEEL
enot-2.1.8.dist-info/entry_points.txt
enot-2.1.8.dist-info/top_level.txt
enot-2.1.8.dist-info/RECORD
