Metadata-Version: 2.1
Name: enot
Version: 2.1.8
Summary: Erlang package management and build system
Home-page: https://github.com/comtihon/enot
Author: Valerii Tikhonov
Author-email: valerii.tikhonov@gmail.com
License: UNKNOWN
Platform: UNKNOWN
Classifier: Programming Language :: Erlang
Classifier: License :: OSI Approved :: Apache Software License
Classifier: Programming Language :: Python :: 3.6
Classifier: Programming Language :: Python :: 3.7
Classifier: Topic :: Software Development :: Build Tools
Requires-Dist: erl-terms
Requires-Dist: docopt
Requires-Dist: gitpython
Requires-Dist: artifactory
Requires-Dist: appdirs
Requires-Dist: boto3
Requires-Dist: Jinja2
Requires-Dist: mock
Requires-Dist: pytest
Requires-Dist: tinydb
Requires-Dist: requests
Requires-Dist: requests-mock
